contour/__init__.py
contour/__main__.py
contour/info.py
contour/main.py
segcontour-1.3.0.dist-info/LICENSE
segcontour-1.3.0.dist-info/METADATA
segcontour-1.3.0.dist-info/WHEEL
segcontour-1.3.0.dist-info/entry_points.txt
segcontour-1.3.0.dist-info/top_level.txt
segcontour-1.3.0.dist-info/RECORD
