Metadata-Version: 2.1
Name: segcontour
Version: 1.3.0
Summary: A semi-automated segmentation and quantitation tool for cyro-soft-X-ray tomography in Python 3
Home-page: https://github.com/kamallouisnahas/Contour
Author: kamallouisnahas
Author-email: contourqueries@gmail.com
License: GPL
Platform: UNKNOWN
Classifier: Programming Language :: Python :: 3
Classifier: License :: OSI Approved :: GNU General Public License v3 (GPLv3)
Classifier: Operating System :: OS Independent
Requires-Python: >3.5
License-File: LICENSE
Requires-Dist: numpy (>=1.21.2)
Requires-Dist: scipy (>=1.7.1)
Requires-Dist: Pillow (>=8.3.2)
Requires-Dist: psutil (>=5.8.0)
